<?xml version="1.0" encoding="euc-kr" ?>
<BlockGame>
    <Screen>
        <Size w="1920" h="1017"></Size>
    </Screen>
    <GamePanel>
        <Bg>bonobonoBg.jpg</Bg>
        <Character>

            <Characterobj1 h="30" w="50" bullet="barbabullet.jpg" img="bonobono.png" y="550" x="325"
            />
        </Character>
        <Block>
            <Obj x="120" y="380" w="50" h="30" img="porori.png" type="1"/>
            <Obj x="170" y="410" w="50" h="30" img="neoburi.png" type="1"/>
            <Obj x="220" y="380" w="50" h="30" img="porori.png" type="1"/>
            <Obj x="270" y="410" w="50" h="30" img="neoburi.png" type="1"/>
            <Obj x="320" y="380" w="50" h="30" img="porori.png" type="1"/>
            <Obj x="370" y="410" w="50" h="30" img="neoburi.png" type="1"/>
            <Obj x="420" y="380" w="50" h="30" img="porori.png" type="1"/>
            <Obj x="470" y="410" w="50" h="30" img="neoburi.png" type="1"/>
            <Obj x="520" y="380" w="50" h="30" img="porori.png" type="1"/>
            <Obj x="570" y="410" w="50" h="30" img="neoburi.png" type="1"/>
            <Obj x="620" y="380" w="50" h="30" img="porori.png" type="1"/>
            <Obj x="670" y="410" w="50" h="30" img="neoburi.png" type="1"/>
            <Obj x="720" y="380" w="50" h="30" img="porori.png" type="1"/>
            <Obj x="770" y="410" w="50" h="30" img="neoburi.png" type="1"/>
            <Obj x="820" y="380" w="50" h="30" img="porori.png" type="1"/>
            <Obj x="870" y="410" w="50" h="30" img="neoburi.png" type="1"/>
            <Obj x="920" y="380" w="50" h="30" img="porori.png" type="1"/>

        </Block>
    </GamePanel>
</BlockGame>
